{
  "data": {
    "name": {
      "value": "block_M5_khoi20"
    },
    "textures": {
      "back": {
        "asset": "asset/map5/m5_khoi20.png"
      },
      "down": {
        "asset": "asset/map5/m5_khoi20.png"
      },
      "front": {
        "asset": "asset/map5/m5_khoi20.png"
      },
      "left": {
        "asset": "asset/map5/m5_khoi20.png"
      },
      "right": {
        "asset": "asset/map5/m5_khoi20.png"
      },
      "up": {
        "asset": "asset/map5/m5_khoi20.png"
      }
    }
  },
  "meta": {
    "EXPORT": {
      "setting.json": "240a9926cce783d3a597bb344fd630a5"
    },
    "VERSION": "0.18"
  }
}